<?xml version="1.0" encoding="utf-8"?>
<Module>
  <ModulePrefs title="評量成績" description="學生、家長-評量成績(國中)">
    <Title lang="zh-TW">評量成績</Title>
    <Icon>icon.png</Icon>
    <Mobile />
    <Title lang="zh-CN">
    </Title>
    <Title lang="en-US">
    </Title>
    <AllowParams>
      <Param key="system_type" type="limit" description="指定為高雄或新竹版">
        <value>kh</value><value>hs</value>
      </Param>
      <Param key="system_exam_must_enddate" type="limit" description="本學期定期成績是否於輸入截止後才顯示成績">
        <value>true</value><value>false</value>
      </Param>
      <Param key="system_fix_must_enddate" type="limit" description="本學期平時成績是否於輸入截止後才顯示成績(僅高雄版有)">
        <value>true</value><value>false</value>
      </Param>
      <Param key="system_show_model" type="limit" description="載入後的預設顯示模式">
        <value>subject</value><value>domain</value>
      </Param>
      <Param key="system_position" type="limit" description="使用小工具者的身份">
        <value>student</value><value>parent</value>
      </Param>
    </AllowParams>
  </ModulePrefs>
</Module>